dictionary/__init__.py
dictionary/dictionary.py
iberq_cs453_hw1-2.0.0.dist-info/METADATA
iberq_cs453_hw1-2.0.0.dist-info/WHEEL
iberq_cs453_hw1-2.0.0.dist-info/top_level.txt
iberq_cs453_hw1-2.0.0.dist-info/RECORD
