Metadata-Version: 2.1
Name: iberq-cs453-hw1
Version: 2.0.0
Summary: UNKNOWN
Author: Ahmet Ayberk Yilmaz
License: UNKNOWN
Platform: UNKNOWN
Requires-Python: >=3.8
Requires-Dist: requests (>=2.23.0)
